mde/__init__.py
mde/cli.py
mde-0.0.2.dist-info/entry_points.txt
mde-0.0.2.dist-info/LICENSE
mde-0.0.2.dist-info/WHEEL
mde-0.0.2.dist-info/METADATA
mde-0.0.2.dist-info/RECORD
