Metadata-Version: 2.1
Name: mde
Version: 0.0.2
Summary: CLI Markdown Editor
License: MIT
Author: Timothy Crosley
Author-email: timothy.crosley@gmail.com
Requires-Python: >=3.6.1,<4.0.0
Classifier: License :: OSI Approved :: MIT License
Classifier: Programming Language :: Python :: 3
Classifier: Programming Language :: Python :: 3.7
Classifier: Programming Language :: Python :: 3.8
Classifier: Programming Language :: Python :: 3.9
Requires-Dist: prompt-toolkit (>=3.0.18,<4.0.0)
Requires-Dist: rich (>=10.1.0,<11.0.0)
